setup.py
acvl_utils/__init__.py
acvl_utils.egg-info/PKG-INFO
acvl_utils.egg-info/SOURCES.txt
acvl_utils.egg-info/dependency_links.txt
acvl_utils.egg-info/requires.txt
acvl_utils.egg-info/top_level.txt
acvl_utils/array_manipulation/__init__.py
acvl_utils/array_manipulation/resampling.py
acvl_utils/array_manipulation/slicer.py
acvl_utils/cropping_and_padding/__init__.py
acvl_utils/cropping_and_padding/bounding_boxes.py
acvl_utils/cropping_and_padding/padding.py
acvl_utils/instance_segmentation/__init__.py
acvl_utils/instance_segmentation/instance_as_semantic_seg.py
acvl_utils/instance_segmentation/instance_matching.py
acvl_utils/miscellaneous/__init__.py
acvl_utils/miscellaneous/ptqdm.py
acvl_utils/miscellaneous/test_all_images_same.py
acvl_utils/morphology/__init__.py
acvl_utils/morphology/gpu_binary_morphology.py
acvl_utils/morphology/morphology_helper.py
acvl_utils/morphology/slice_interpolation.py
tests/test_component_removal.py
tests/test_crop_and_pad.py
tests/test_insert_crop.py
tests/test_instance_matching.py
tests/test_padding.py
tests/test_ptqdm.py
tests/test_slicer.py