Metadata-Version: 2.1
Name: acvl_utils
Version: 0.2.1
Summary: Super cool utilities that we just love to use
Author: Applied Computer Vision Lab, Helmholtz Imaging & Division of Medical Image Computing, German Cancer Research Center
Author-email: f.isensee@dkfz.de
License: Apache License Version 2.0, January 2004
Requires-Dist: numpy
Requires-Dist: batchgenerators
Requires-Dist: torch
Requires-Dist: SimpleITK
Requires-Dist: scikit-image
Requires-Dist: connected-components-3d
